arprint/__init__.py
arprint-0.1.2.dist-info/METADATA
arprint-0.1.2.dist-info/WHEEL
arprint-0.1.2.dist-info/top_level.txt
arprint-0.1.2.dist-info/RECORD
