Metadata-Version: 2.4
Name: arprint
Version: 0.1.2
Summary: A library to print and input Arabic text correctly in terminal with color support
Home-page: https://github.com/cymoussa/arprint
Author: youcef
Author-email: youcef.dev0@gmail.com
Keywords: arabic,terminal,print,input,bidi,reshaper,cybersecurity,arprint
Classifier: Programming Language :: Python :: 3
Classifier: License :: OSI Approved :: MIT License
Classifier: Operating System :: OS Independent
Classifier: Topic :: Software Development :: Libraries :: Python Modules
Classifier: Intended Audience :: Developers
Requires-Python: >=3.6
Requires-Dist: arabic-reshaper
Requires-Dist: python-bidi
Dynamic: author
Dynamic: author-email
Dynamic: classifier
Dynamic: description
Dynamic: description-content-type
Dynamic: home-page
Dynamic: keywords
Dynamic: requires-dist
Dynamic: requires-python
Dynamic: summary
